Metadata-Version: 1.2
Name: LibPrep
Version: 1.1.1
Summary: Python package to analyse and prepare libraries of chemical compounds for molecular simulations.
Home-page: https://github.com/carlesperez94/lib_prep
Author: Carles Perez Lopez
Author-email: carlesperez94@gmail.com
License: UNKNOWN
Project-URL: Documentation, https://carlesperez94.github.io/lib_prep/
Project-URL: Source, https://carlesperez94.github.io/lib_prep/
Project-URL: Tracker, https://github.com/carlesperez94/lib_prep/issues
Platform: UNKNOWN
Classifier: Programming Language :: Python :: 3
Classifier: License :: OSI Approved :: MIT License
Classifier: Operating System :: POSIX :: Linux
Classifier: Intended Audience :: Science/Research
